wagtaillinkchecker/__init__.py
wagtaillinkchecker/apps.py
wagtaillinkchecker/forms.py
wagtaillinkchecker/models.py
wagtaillinkchecker/pagination.py
wagtaillinkchecker/scanner.py
wagtaillinkchecker/tasks.py
wagtaillinkchecker/urls.py
wagtaillinkchecker/utils.py
wagtaillinkchecker/views.py
wagtaillinkchecker/wagtail_hooks.py
wagtaillinkchecker/management/__init__.py
wagtaillinkchecker/management/commands/__init__.py
wagtaillinkchecker/management/commands/linkcheck.py
wagtaillinkchecker/migrations/0001_initial.py
wagtaillinkchecker/migrations/0002_auto_20160209_1533.py
wagtaillinkchecker/migrations/0003_store_scan_results.py
wagtaillinkchecker/migrations/0004_auto_20180829_1922.py
wagtaillinkchecker/migrations/0005_auto_20180922_1835.py
wagtaillinkchecker/migrations/__init__.py
wagtaillinkchecker/templates/wagtaillinkchecker/delete.html
wagtaillinkchecker/templates/wagtaillinkchecker/index.html
wagtaillinkchecker/templates/wagtaillinkchecker/results.html
wagtaillinkchecker/templates/wagtaillinkchecker/scan.html
wagtaillinkchecker/templates/wagtaillinkchecker/scan_list.html
wagtaillinkchecker/templates/wagtaillinkchecker/settings.html
wagtaillinkchecker/templates/wagtaillinkchecker/emails/broken_links.html
wagtail_linkchecker-0.6.0.dist-info/LICENSE
wagtail_linkchecker-0.6.0.dist-info/METADATA
wagtail_linkchecker-0.6.0.dist-info/WHEEL
wagtail_linkchecker-0.6.0.dist-info/top_level.txt
wagtail_linkchecker-0.6.0.dist-info/RECORD
