Metadata-Version: 2.1
Name: wagtail-linkchecker
Version: 0.6.0
Summary: A tool to assist with finding broken links on your wagtail site.
Home-page: https://github.com/neon-jungle/wagtail-linkchecker/
Author: Neon Jungle
Author-email: developers@neonjungle.studio
License: BSD License
Platform: UNKNOWN
Classifier: Environment :: Web Environment
Classifier: Intended Audience :: Developers
Classifier: Operating System :: OS Independent
Classifier: Programming Language :: Python
Classifier: Framework :: Django
Classifier: License :: OSI Approved :: BSD License
License-File: LICENSE
Requires-Dist: wagtail (>=1.0)
Requires-Dist: requests (>=2.9.1)
Requires-Dist: celery (<5,>=4.0)
